{"college":"School of Medicine","dept":"Microbiology and Molecular Genetics","course":"MICROBIAL PATHOGENI","code":"92502","type":"Res","sec":"2","unit":"2-12","instructor":"BARBOUR, A.","time":"      TBA","place":"TBA","final":"    TBA","max":"40","enr":"1"}
{"college":"School of Medicine","dept":"Microbiology and Molecular Genetics","course":"MOLEC NEUROBIOL","code":"92504","type":"Res","sec":"4","unit":"2-12","instructor":"GOLDIN, A.","time":"      TBA","place":"TBA","final":"    TBA","max":"40","enr":"3"}
{"college":"School of Medicine","dept":"Microbiology and Molecular Genetics","course":"MOL GEN/RECOMB DNA","code":"92506","type":"Res","sec":"6","unit":"2-12","instructor":"HATFIELD, G.","time":"      TBA","place":"TBA","final":"    TBA","max":"40","enr":"0"}
{"college":"School of Medicine","dept":"Microbiology and Molecular Genetics","course":"REG OF PRE-MRNA SPL","code":"92507","type":"Res","sec":"7","unit":"2-12","instructor":"HERTEL, K.","time":"      TBA","place":"TBA","final":"    TBA","max":"40","enr":"3"}
{"college":"School of Medicine","dept":"Microbiology and Molecular Genetics","course":"MUCOSAL IMMUNITY","code":"92511","type":"Res","sec":"11","unit":"2-12","instructor":"OUELLETTE, A.","time":"      TBA","place":"TBA","final":"    TBA","max":"40","enr":"0"}
{"college":"School of Medicine","dept":"Microbiology and Molecular Genetics","course":"PRIM RETRO VIROLOGY","code":"92512","type":"Res","sec":"12","unit":"2-12","instructor":"ROBINSON, W.","time":"      TBA","place":"TBA","final":"    TBA","max":"40","enr":"0"}
{"college":"School of Medicine","dept":"Microbiology and Molecular Genetics","course":"VIROLOGY","code":"92514","type":"Res","sec":"14","unit":"2-12","instructor":"SANDRI-GOLDIN, R.","time":"      TBA","place":"TBA","final":"    TBA","max":"40","enr":"1"}
{"college":"School of Medicine","dept":"Microbiology and Molecular Genetics","course":"BACTERIAL PATHOGENE","code":"92519","type":"Res","sec":"19","unit":"2-12","instructor":"TAN, M.","time":"      TBA","place":"TBA","final":"    TBA","max":"40","enr":"1"}
{"college":"School of Medicine","dept":"Microbiology and Molecular Genetics","course":"MICROBIOL & MOL GEN","code":"92520","type":"Res","sec":"20","unit":"2-12","instructor":"WATERMAN, M.","time":"      TBA","place":"TBA","final":"    TBA","max":"40","enr":"3"}
{"college":"School of Medicine","dept":"Microbiology and Molecular Genetics","course":"IMMUNO & AUTO IMMUN","code":"92521","type":"Res","sec":"21","unit":"2-12","instructor":"DEMETRIOU, M.","time":"      TBA","place":"TBA","final":"    TBA","max":"40","enr":"3"}
{"college":"School of Medicine","dept":"Microbiology and Molecular Genetics","course":"MICROBIOL & MOL GEN","code":"92523","type":"Res","sec":"23","unit":"2-12","instructor":"APHASIZHEV, R.","time":"      TBA","place":"TBA","final":"    TBA","max":"40","enr":"0"}
{"college":"School of Medicine","dept":"Microbiology and Molecular Genetics","course":"GENE EXPRESSION","code":"92527","type":"Res","sec":"27","unit":"2-12","instructor":"SASSONE-CORSI, P.","time":"      TBA","place":"TBA","final":"    TBA","max":"40","enr":"0"}
{"college":"School of Medicine","dept":"Microbiology and Molecular Genetics","course":"MICROBIOL & MOL GEN","code":"92529","type":"Res","sec":"29","unit":"2-12","instructor":"BORRELLI, E.","time":"      TBA","place":"TBA","final":"    TBA","max":"40","enr":"2"}
{"college":"School of Medicine","dept":"Microbiology and Molecular Genetics","course":"MICROBIOL & MOL GEN","code":"92533","type":"Res","sec":"33","unit":"2-12","instructor":"SHI, Y.","time":"      TBA","place":"TBA","final":"    TBA","max":"40","enr":"1"}
{"college":"School of Medicine","dept":"Microbiology and Molecular Genetics","course":"FIRST YEAR RESEARCH","code":"92552","type":"Lab","sec":"B","unit":"2-12","instructor":"APHASIZHEV, R.","time":"      TBA","place":"TBA","final":"    TBA","max":"40","enr":"0"}
{"college":"School of Medicine","dept":"Microbiology and Molecular Genetics","course":"FIRST YEAR RESEARCH","code":"92556","type":"Lab","sec":"D","unit":"2-12","instructor":"BORRELLI, E.","time":"      TBA","place":"TBA","final":"    TBA","max":"40","enr":"0"}
{"college":"School of Medicine","dept":"Microbiology and Molecular Genetics","course":"FIRST YEAR RESEARCH","code":"92560","type":"Lab","sec":"F","unit":"2-12","instructor":"GOLDIN, A.","time":"      TBA","place":"TBA","final":"    TBA","max":"40","enr":"0"}
{"college":"School of Medicine","dept":"Microbiology and Molecular Genetics","course":"FIRST YEAR RESEARCH","code":"92564","type":"Lab","sec":"H","unit":"2-12","instructor":"HERTEL, K.","time":"      TBA","place":"TBA","final":"    TBA","max":"40","enr":"0"}
{"college":"School of Medicine","dept":"Microbiology and Molecular Genetics","course":"FIRST YEAR RESEARCH","code":"92568","type":"Lab","sec":"J","unit":"2-12","instructor":"OUELLETTE, A.","time":"      TBA","place":"TBA","final":"    TBA","max":"40","enr":"0"}
{"college":"School of Medicine","dept":"Microbiology and Molecular Genetics","course":"FIRST YEAR RESEARCH","code":"92572","type":"Lab","sec":"L","unit":"2-12","instructor":"SANDRI-GOLDIN, R.","time":"      TBA","place":"TBA","final":"    TBA","max":"40","enr":"1"}
{"college":"School of Medicine","dept":"Microbiology and Molecular Genetics","course":"FIRST YEAR RESEARCH","code":"92576","type":"Lab","sec":"N","unit":"2-12","instructor":"SEMLER, B.","time":"      TBA","place":"TBA","final":"    TBA","max":"40","enr":"0"}
{"college":"School of Medicine","dept":"Microbiology and Molecular Genetics","course":"FIRST YEAR RESEARCH","code":"92580","type":"Lab","sec":"P","unit":"2-12","instructor":"WATERMAN, M.","time":"      TBA","place":"TBA","final":"    TBA","max":"40","enr":"0"}
{"college":"School of Medicine","dept":"Microbiology and Molecular Genetics","course":"FIRST YEAR RESEARCH","code":"92584","type":"Lab","sec":"R","unit":"2-12","instructor":"SHI, Y.","time":"      TBA","place":"TBA","final":"    TBA","max":"40","enr":"0"}
{"college":"School of Medicine","dept":"Microbiology and Molecular Genetics","course":"RES TOPICS M & MG","code":"92600","type":"Sem","sec":"A","unit":"1","instructor":"SANDRI-GOLDIN, R.","time":"Th    9:00- 9:50 ","place":"TBA","final":"    TBA","max":"100","enr":"27"}
{"college":"School of Medicine","dept":"Microbiology and Molecular Genetics","course":"ADV STUDIES M&MG","code":"92602","type":"Tut","sec":"A","unit":"1","instructor":"BARBOUR, A.","time":"      TBA","place":"TBA","final":"    TBA","max":"40","enr":"1"}
{"college":"School of Medicine","dept":"Microbiology and Molecular Genetics","course":"ADV STUDIES M&MG","code":"92608","type":"Tut","sec":"F","unit":"1","instructor":"HERTEL, K.","time":"      TBA","place":"TBA","final":"    TBA","max":"40","enr":"3"}
{"college":"School of Medicine","dept":"Microbiology and Molecular Genetics","course":"ADV STUDIES M&MG","code":"92612","type":"Tut","sec":"H","unit":"1","instructor":"ROBINSON, W.","time":"      TBA","place":"TBA","final":"    TBA","max":"40","enr":"0"}
{"college":"School of Medicine","dept":"Microbiology and Molecular Genetics","course":"ADV STUDIES M&MG","code":"92616","type":"Tut","sec":"K","unit":"1","instructor":"SEMLER, B.","time":"      TBA","place":"TBA","final":"    TBA","max":"40","enr":"5"}
{"college":"School of Medicine","dept":"Microbiology and Molecular Genetics","course":"ADV STUDIES M&MG","code":"92620","type":"Tut","sec":"N","unit":"1","instructor":"WATERMAN, M.","time":"      TBA","place":"TBA","final":"    TBA","max":"40","enr":"3"}
{"college":"School of Medicine","dept":"Microbiology and Molecular Genetics","course":"ADV STUDIES M&MG","code":"92624","type":"Tut","sec":"P","unit":"1","instructor":"APHASIZHEV, R.","time":"      TBA","place":"TBA","final":"    TBA","max":"40","enr":"0"}
{"college":"School of Medicine","dept":"Microbiology and Molecular Genetics","course":"ADV STUDIES M&MG","code":"92628","type":"Tut","sec":"R","unit":"1","instructor":"SASSONE-CORSI, P.","time":"      TBA","place":"TBA","final":"    TBA","max":"40","enr":"0"}
{"college":"School of Medicine","dept":"Microbiology and Molecular Genetics","course":"ADV STUDIES M&MG","code":"92632","type":"Tut","sec":"U","unit":"1","instructor":"RAFFATELLU, M.","time":"      TBA","place":"TBA","final":"    TBA","max":"40","enr":"4"}
{"college":"School of Medicine","dept":"Microbiology and Molecular Genetics","course":"ADV STUDIES M&MG","code":"92636","type":"Tut","sec":"B","unit":"1","instructor":"CASALI, P.","time":"      TBA","place":"TBA","final":"    TBA","max":"40","enr":"0"}
{"college":"School of Medicine","dept":"Microbiology and Molecular Genetics","course":"REG GENE EXPRESSION","code":"92706","type":"Lec","sec":"A","unit":"4","instructor":"HERTEL, K.WATERMAN, M.SHI, Y.","time":"MWF    9:00-10:50 ","place":"DBH 1429","final":"Wed, Jun 12, 8:00-10:00am","max":"17","enr":"15"}
{"college":"School of Medicine","dept":"Microbiology and Molecular Genetics","course":"MOLEC PATH VIR INF","code":"92720","type":"Lec","sec":"A","unit":"4","instructor":"ROBINSON, W.SANDRI-GOLDIN, R.SEMLER, B.","time":"TuTh    1:30- 2:50p","place":"TBA","final":"    TBA","max":"999","enr":"0"}
{"college":"School of Medicine","dept":"Microbiology and Molecular Genetics","course":"IMMUNOL JOURNL CLUB","code":"92727","type":"Lec","sec":"A","unit":"2","instructor":"CASALI, P.WALSH, C.","time":"W   12:00-12:50p","place":"MH 3248","final":"    TBA","max":"20","enr":"6 / 16"}
{"college":"School of Medicine","dept":"Microbiology and Molecular Genetics","course":"TOPICS STEM CELLS","code":"92730","type":"Lec","sec":"C","unit":"2-4","instructor":"GOLUB, S.CUMMINGS, B.","time":"F   11:00-12:50p","place":"TBA","final":"    TBA","max":"24","enr":"15 / 17"}
{"college":"School of Medicine","dept":"Microbiology and Molecular Genetics","course":"M.D./PH.D. TUTORIAL","code":"92740","type":"Tut","sec":"A","unit":"1","instructor":"GOLDIN, A.","time":"      TBA","place":"TBA","final":"    TBA","max":"100","enr":"14"}
{"college":"School of Medicine","dept":"Microbiology and Molecular Genetics","course":"CONDUCT OF RESEARCH","code":"92750","type":"Lec","sec":"A","unit":"2","instructor":"GOLDIN, A.","time":"W    2:00- 3:20p","place":"TBA","final":"    TBA","max":"80","enr":"49"}
{"college":"School of Medicine","dept":"Microbiology and Molecular Genetics","course":"CAREER DEVELOPEMENT","code":"92770","type":"Tut","sec":"C","unit":"2","instructor":"GOLDIN, A.","time":"      TBA","place":"TBA","final":"    TBA","max":"100","enr":"0"}
{"college":"School of Medicine","dept":"Microbiology and Molecular Genetics","course":"TUTORIAL IN M&MG","code":"92780","type":"Tut","sec":"A","unit":"2","instructor":"SANDRI-GOLDIN, R.","time":"      TBA","place":"TBA","final":"    TBA","max":"12","enr":"9"}
{"college":"School of Medicine","dept":"Microbiology and Molecular Genetics","course":"SCIENTIFIC COMMUNCN","code":"92900","type":"Sem","sec":"A","unit":"2","instructor":"BORRELLI, E.","time":"      TBA","place":"TBA","final":"    TBA","max":"40","enr":"1"}
{"college":"School of Medicine","dept":"Microbiology and Molecular Genetics","course":"SCIENTIFIC COMMUNCN","code":"92904","type":"Sem","sec":"D","unit":"2","instructor":"SEMLER, B.","time":"      TBA","place":"TBA","final":"    TBA","max":"100","enr":"0"}
{"college":"School of Medicine","dept":"Microbiology and Molecular Genetics","course":"SCIENTIFIC COMMUNCN","code":"92908","type":"Sem","sec":"D","unit":"2","instructor":"RAFFATELLU, M.","time":"      TBA","place":"TBA","final":"    TBA","max":"100","enr":"1"}
{"college":"School of Medicine","dept":"Microbiology and Molecular Genetics","course":"SCIENTIFIC COMMUNCN","code":"92912","type":"Sem","sec":"A","unit":"2","instructor":"HERTEL, K.","time":"      TBA","place":"TBA","final":"    TBA","max":"40","enr":"0"}
{"college":"School of Medicine","dept":"Microbiology and Molecular Genetics","course":"INDEPENDENT STUDY","code":"92990","type":"Tut","sec":"B","unit":"1-12","instructor":"GOLDIN, A.","time":"      TBA","place":"TBA","final":"    TBA","max":"250","enr":"7"}
