{ "college":"Paul Merage School of Business","dept":"Management MBA","course":"MGMT SCIENCE","code":"38510","ctype":"Lec","sec":"1","unit":"2","instructor":"JORJANI, SADRI, S.","weekday":"M","timestr":"8:30-9:50","stop":time:("9:50:00"),"start":time:("8:30:00"),"place":"SB 122","final":"    TBA","max":60,"enr":"56" }
{ "college":"Paul Merage School of Business","dept":"Management MBA","course":"MGMT SCIENCE","code":"38512","ctype":"Dis","sec":"X","unit":"0","instructor":"STAFF","weekday":"M","timestr":"2:30-3:50p","stop":time:("15:50:00"),"start":time:("14:30:00"),"place":"SB 122","final":" ","max":40,"enr":"0" }
{ "college":"Paul Merage School of Business","dept":"Management MBA","course":"OPERATIONS MGMT","code":"38555","ctype":"Lec","sec":"1","unit":"4","instructor":"SO, K.C.","weekday":"W","timestr":"8:30-11:20","stop":time:("11:20:00"),"start":time:("8:30:00"),"place":"SB 117","final":"    TBA","max":60,"enr":"55" }
{ "college":"Paul Merage School of Business","dept":"Management MBA","course":"OPERATIONS MGMT","code":"38557","ctype":"Dis","sec":"X","unit":"0","instructor":"STAFF","weekday":"M","timestr":"1:00-2:20p","stop":time:("14:20:00"),"start":time:("13:00:00"),"place":"SB 117","final":" ","max":40,"enr":"0" }
{ "college":"Paul Merage School of Business","dept":"Management MBA","course":"BUSINESS STRATEGY","code":"38565","ctype":"Lec","sec":"1","unit":"4","instructor":"BROMILEY, P.","weekday":"Tu","timestr":"1:00-3:50p","stop":time:("15:50:00"),"start":time:("13:00:00"),"place":"SB 122","final":"    TBA","max":60,"enr":"57" }
{ "college":"Paul Merage School of Business","dept":"Management MBA","course":"MBA PROSEMINAR","code":"38574","ctype":"Sem","sec":"1","unit":"0","instructor":"VENKATESH, A.","weekday":"Tu","timestr":"10:00-11:50","stop":time:("11:50:00"),"start":time:("10:00:00"),"place":"SB 116","final":"    TBA","max":40,"enr":"50" }
{ "college":"Paul Merage School of Business","dept":"Management MBA","course":"MBA PROSEMINAR","code":"38578","ctype":"Sem","sec":"3","unit":"0","instructor":"VENKATESH, A.","weekday":"Sa","timestr":"1:00-2:50p","stop":time:("14:50:00"),"start":time:("13:00:00"),"place":"SB 223","final":"    TBA","max":15,"enr":"9" }
{ "college":"Paul Merage School of Business","dept":"Management MBA","course":"GLOBAL STRATEGY","code":"38595","ctype":"Sem","sec":"ST","unit":"4","instructor":"POSTREL, S.","weekday":"Th","timestr":"1:00-3:50p","stop":time:("15:50:00"),"start":time:("13:00:00"),"place":"SB 223","final":"    TBA","max":40,"enr":"19" }
{ "college":"Paul Merage School of Business","dept":"Management MBA","course":"INTERNATIONAL MGMT","code":"38650","ctype":"Sem","sec":"OM","unit":"4","instructor":"HERNANDEZ, W.","weekday":"Tu","timestr":"8:30-11:20","stop":time:("11:20:00"),"start":time:("8:30:00"),"place":"SB 112","final":"    TBA","max":40,"enr":"31" }
{ "college":"Paul Merage School of Business","dept":"Management MBA","course":"EARNINGS&ASSET ANYS","code":"38661","ctype":"Sem","sec":"AC","unit":"4","instructor":"HIRSHLEIFER, S.","weekday":"Th","timestr":"4:00-6:50p","stop":time:("18:50:00"),"start":time:("16:00:00"),"place":"SB 223","final":"    TBA","max":40,"enr":"36" }
{ "college":"Paul Merage School of Business","dept":"Management MBA","course":"CORPORATE VALUATION","code":"38735","ctype":"Sem","sec":"FN","unit":"4","instructor":"ZHENG, L.","weekday":"Tu","timestr":"4:00-6:50p","stop":time:("18:50:00"),"start":time:("16:00:00"),"place":"SB 122","final":"    TBA","max":40,"enr":"33" }
{ "college":"Paul Merage School of Business","dept":"Management MBA","course":"INTRO REAL ESTATE","code":"38745","ctype":"Sem","sec":"RE","unit":"4","instructor":"VANDELL, K.","weekday":"M","timestr":"7:00-9:50p","stop":time:("21:50:00"),"start":time:("19:00:00"),"place":"MPAA 120","final":"    TBA","max":50,"enr":"46" }
{ "college":"Paul Merage School of Business","dept":"Management MBA","course":"MGMT RE ENTERPRISE","code":"38755","ctype":"Sem","sec":"RE","unit":"4","instructor":"STRADER, T.","weekday":"W","timestr":"7:00-9:50p","stop":time:("21:50:00"),"start":time:("19:00:00"),"place":"SB 116","final":"    TBA","max":20,"enr":"18" }
{ "college":"Paul Merage School of Business","dept":"Management MBA","course":"CONSUMER BEHAVIOR","code":"38760","ctype":"Sem","sec":"MK","unit":"4","instructor":"LAU-GESK, L.","weekday":"W","timestr":"1:00-3:50p","stop":time:("15:50:00"),"start":time:("13:00:00"),"place":"SB 122","final":"    TBA","max":40,"enr":"23" }
{ "college":"Paul Merage School of Business","dept":"Management MBA","course":"NEW PRODUCT DEV","code":"38775","ctype":"Sem","sec":"MK","unit":"4","instructor":"TYAGI, R.","weekday":"W","timestr":"1:00-3:50p","stop":time:("15:50:00"),"start":time:("13:00:00"),"place":"SB 112","final":"    TBA","max":40,"enr":"31" }
{ "college":"Paul Merage School of Business","dept":"Management MBA","course":"DECISION ANALYSIS","code":"38920","ctype":"Sem","sec":"OD","unit":"4","instructor":"KELLER, L.","weekday":"Th","timestr":"4:00-6:50p","stop":time:("18:50:00"),"start":time:("16:00:00"),"place":"SB 122","final":"    TBA","max":40,"enr":"25" }
{ "college":"Paul Merage School of Business","dept":"Management MBA","course":"BUS OF MEDICINE","code":"38956","ctype":"Sem","sec":"HC","unit":"4","instructor":"BATRA, R.","weekday":"Th","timestr":"7:00-9:50p","stop":time:("21:50:00"),"start":time:("19:00:00"),"place":"SB 116","final":"    TBA","max":34,"enr":"34" }
{ "college":"Paul Merage School of Business","dept":"Management MBA","course":"CREATIVITY&INNOVA","code":"38962","ctype":"Sem","sec":"OM","unit":"4","instructor":"BARRON, L.","weekday":"Tu","timestr":"4:00-6:50p","stop":time:("18:50:00"),"start":time:("16:00:00"),"place":"SB 116","final":"    TBA","max":30,"enr":"26" }
{ "college":"Paul Merage School of Business","dept":"Management MBA","course":"EDGE","code":"38965","ctype":"Sem","sec":"A","unit":"4","instructor":"GURBAXANI, V.STANLEY, T.","weekday":"Tu","timestr":"1:00-3:50p","stop":time:("15:50:00"),"start":time:("13:00:00"),"place":"MPAA 120","final":"    TBA","max":40,"enr":"21" }
{ "college":"Paul Merage School of Business","dept":"Management MBA","course":"SUST&COMPET ADV","code":"38966","ctype":"Sem","sec":"B","unit":"4","instructor":"JAY, J.","weekday":"F","timestr":"8:30-11:20","stop":time:("11:20:00"),"start":time:("8:30:00"),"place":"SB 223","final":"    TBA","max":40,"enr":"35" }
{ "college":"Paul Merage School of Business","dept":"Management MBA","course":"INDIVIDUAL STUDY","code":"38974","ctype":"Tut","sec":"A","unit":"1-12","instructor":"ZHENG, L.","weekday":" ","timestr":"","place":"TBA","final":"    TBA","max":10,"enr":"1" }
{ "college":"Paul Merage School of Business","dept":"Management MBA","course":"INDIVIDUAL STUDY","code":"38977","ctype":"Tut","sec":"B","unit":"1-12","instructor":"HUANG, C.","weekday":" ","timestr":"","place":"TBA","final":"    TBA","max":10,"enr":"1" }
{ "college":"Paul Merage School of Business","dept":"Management MBA","course":"INDIVIDUAL STUDY","code":"38979","ctype":"Tut","sec":"D","unit":"1-12","instructor":"ZHANG, Y.","weekday":" ","timestr":"","place":"TBA","final":"    TBA","max":10,"enr":"6" }
{ "college":"Paul Merage School of Business","dept":"Management MBA","course":"MICROMARKETING LAB","code":"38980","ctype":"Sem","sec":"A","unit":"2","instructor":"PECHMANN, C.","weekday":"M","timestr":"10:30-11:50","stop":time:("11:50:00"),"start":time:("10:30:00"),"place":"SB 223","final":"    TBA","max":35,"enr":"21" }
{ "college":"Paul Merage School of Business","dept":"Management MBA","course":"MICROMARKETING LAB","code":"38982","ctype":"Dis","sec":"1","unit":"0","instructor":"STAFF","weekday":"M","timestr":"3:30-4:50p","stop":time:("16:50:00"),"start":time:("15:30:00"),"place":"SB 223","final":" ","max":35,"enr":"2" }
{ "college":"Paul Merage School of Business","dept":"Management MBA","course":"INDIVIDUAL STUDY","code":"38989","ctype":"Tut","sec":"E","unit":"1-12","instructor":"SHIVENDU, S.","weekday":" ","timestr":"","place":"TBA","final":"    TBA","max":10,"enr":"5" }
{ "college":"Paul Merage School of Business","dept":"Management MBA","course":"INDIVIDUAL STUDY","code":"38991","ctype":"Tut","sec":"G","unit":"1-12","instructor":"NAVARRO, P.","weekday":" ","timestr":"","place":"TBA","final":"    TBA","max":10,"enr":"1" }
{ "college":"Paul Merage School of Business","dept":"Management MBA","course":"INDIVIDUAL STUDY","code":"38993","ctype":"Tut","sec":"I","unit":"1-12","instructor":"KELLER, L.","weekday":" ","timestr":"","place":"TBA","final":"    TBA","max":10,"enr":"1" }
{ "college":"Paul Merage School of Business","dept":"Management MBA","course":"INDIVIDUAL STUDY","code":"38995","ctype":"Tut","sec":"K","unit":"1-12","instructor":"OKHUYSEN, G.","weekday":" ","timestr":"","place":"TBA","final":"    TBA","max":10,"enr":"3" }
{ "college":"Paul Merage School of Business","dept":"Management MBA","course":"INDIVIDUAL STUDY","code":"38999","ctype":"Tut","sec":"M","unit":"1-12","instructor":"TRAPIDO, D.","weekday":" ","timestr":"","place":"TBA","final":"    TBA","max":10,"enr":"1" }
{ "college":"Paul Merage School of Business","dept":"Management MBA","course":"BUS TECH STR CONSLT","code":"39644","ctype":"Sem","sec":"A","unit":"4","instructor":"TRAINOR, H.","weekday":"W","timestr":"7:00-9:50p","stop":time:("21:50:00"),"start":time:("19:00:00"),"place":"MPAA 330","final":"    TBA","max":30,"enr":"14" }
