{ "college":"Henry Samueli School of Engineering","dept":"Engineering","course":"DYNAMICS","code":"13005","ctype":"Lec","sec":"A","unit":"4","instructor":"BISHAY, P.STAFF","weekday":"MWF","timestr":"9:00-9:50","stop":time:("9:50:00"),"start":time:("9:00:00"),"place":"EH 1200","final":"Wed, Jun 12, 8:00-10:00am","max":225,"enr":"11 / 151" }
{ "college":"Henry Samueli School of Engineering","dept":"Engineering","course":"DYNAMICS","code":"13008","ctype":"Dis","sec":"A2","unit":"0","instructor":"BISHAY, P.STAFF","weekday":"W","timestr":"3:00-3:50p","stop":time:("15:50:00"),"start":time:("15:00:00"),"place":"ET 202","final":" ","max":45,"enr":"0 / 3" }
{ "college":"Henry Samueli School of Engineering","dept":"Engineering","course":"DYNAMICS","code":"13010","ctype":"Dis","sec":"A4","unit":"0","instructor":"BISHAY, P.STAFF","weekday":"Th","timestr":"12:00-12:50p","stop":time:("12:50:00"),"start":time:("12:00:00"),"place":"SSTR 100","final":" ","max":45,"enr":"2 / 45" }
{ "college":"Henry Samueli School of Engineering","dept":"Engineering","course":"PUB & PROF SERVICE","code":"13015","ctype":"Act","sec":"A","unit":"1","instructor":"LARUE, J.JEFFERS, R.","weekday":"W","timestr":"7:00-7:50p","stop":time:("19:50:00"),"start":time:("19:00:00"),"place":"ELH 110","final":"Wed, Jun 12, 7:00-9:00pm","max":50,"enr":"8" }
{ "college":"Henry Samueli School of Engineering","dept":"Engineering","course":"PROJ ENGR 2A","code":"13030","ctype":"Lec","sec":"B","unit":"1","instructor":"MCCARTHY, J.","weekday":"TuTh","timestr":"7:00-8:50p","stop":time:("20:50:00"),"start":time:("19:00:00"),"place":"DBH 1431","final":"Tue, Jun 11, 7:00-9:00pm","max":20,"enr":"2" }
{ "college":"Henry Samueli School of Engineering","dept":"Engineering","course":"PROJ ENGR 2A","code":"13032","ctype":"Lab","sec":"B2","unit":"0","instructor":"MCCARTHY, J.","weekday":"Tu","timestr":"10:00-11:50","stop":time:("11:50:00"),"start":time:("10:00:00"),"place":"ET 141","final":" ","max":20,"enr":"0" }
{ "college":"Henry Samueli School of Engineering","dept":"Engineering","course":"PROJ ENGR 2A","code":"13034","ctype":"Lab","sec":"B4","unit":"0","instructor":"MCCARTHY, J.","weekday":"Th","timestr":"10:00-11:50","stop":time:("11:50:00"),"start":time:("10:00:00"),"place":"ET 141","final":" ","max":20,"enr":"1" }
{ "college":"Henry Samueli School of Engineering","dept":"Engineering","course":"PROJ ENGR 2A","code":"13040","ctype":"Lec","sec":"D","unit":"1-4","instructor":"VILLAC, B.","weekday":"W","timestr":"7:00-9:50p","stop":time:("21:50:00"),"start":time:("19:00:00"),"place":"TBA","final":"Wed, Jun 12, 7:00-9:00pm","max":30,"enr":"3" }
{ "college":"Henry Samueli School of Engineering","dept":"Engineering","course":"PROJ ENGR 2A","code":"13044","ctype":"Lec","sec":"F","unit":"1-4","instructor":"BOBROW, J.","weekday":" ","timestr":"","place":"TBA","final":"    TBA","max":15,"enr":"0" }
{ "college":"Henry Samueli School of Engineering","dept":"Engineering","course":"ITE PROJECT","code":"13048","ctype":"Lab","sec":"A","unit":"2","instructor":"RITCHIE, S.","weekday":"W","timestr":"12:00-12:50p","stop":time:("12:50:00"),"start":time:("12:00:00"),"place":"ELH 110","final":"    TBA","max":40,"enr":"23" }
{ "college":"Henry Samueli School of Engineering","dept":"Engineering","course":"COMM IN PROF WORLD","code":"13050","ctype":"Lec","sec":"A","unit":"4","instructor":"STUPAR, J.","weekday":"MW","timestr":"8:00-9:50","stop":time:("9:50:00"),"start":time:("8:00:00"),"place":"ET 201","final":"    TBA","max":22,"enr":"22" }
{ "college":"Henry Samueli School of Engineering","dept":"Engineering","course":"COMM IN PROF WORLD","code":"13060","ctype":"Lec","sec":"B","unit":"4","instructor":"STUPAR, J.","weekday":"MW","timestr":"10:00-11:50","stop":time:("11:50:00"),"start":time:("10:00:00"),"place":"ET 201","final":"Mon, Jun 10, 10:30-12:30pm","max":22,"enr":"22" }
{ "college":"Henry Samueli School of Engineering","dept":"Engineering","course":"COMM IN PROF WORLD","code":"13070","ctype":"Lec","sec":"C","unit":"4","instructor":"STUPAR, J.","weekday":"TuTh","timestr":"8:00-9:50","stop":time:("9:50:00"),"start":time:("8:00:00"),"place":"ET 201","final":"Tue, Jun 11, 8:00-10:00am","max":22,"enr":"22" }
{ "college":"Henry Samueli School of Engineering","dept":"Engineering","course":"COMM IN PROF WORLD","code":"13080","ctype":"Lec","sec":"D","unit":"4","instructor":"BACH, S.","weekday":"MW","timestr":"11:00-12:50p","stop":time:("12:50:00"),"start":time:("11:00:00"),"place":"DBH 1423","final":"Tue, Jun 11, 1:30-3:30pm","max":22,"enr":"22" }
{ "college":"Henry Samueli School of Engineering","dept":"Engineering","course":"COMM IN PROF WORLD","code":"13090","ctype":"Lec","sec":"E","unit":"4","instructor":"FORESTA, J.","weekday":"TuTh","timestr":"7:00-8:50p","stop":time:("20:50:00"),"start":time:("19:00:00"),"place":"ET 201","final":"Tue, Jun 11, 7:00-9:00pm","max":22,"enr":"23" }
{ "college":"Henry Samueli School of Engineering","dept":"Engineering","course":"COMM IN PROF WORLD","code":"13095","ctype":"Lec","sec":"F","unit":"4","instructor":"HONG, P.","weekday":"MW","timestr":"8:00-9:50","stop":time:("9:50:00"),"start":time:("8:00:00"),"place":"DBH 1427","final":"    TBA","max":22,"enr":"16" }
{ "college":"Henry Samueli School of Engineering","dept":"Engineering","course":"HONORS THESIS","code":"13120","ctype":"Tut","sec":"A","unit":"4","instructor":"BOYRAZ, O.","weekday":"M","timestr":"6:00-6:50p","stop":time:("18:50:00"),"start":time:("18:00:00"),"place":"TBA","final":"    TBA","max":10,"enr":"0" }
{ "college":"Henry Samueli School of Engineering","dept":"Engineering","course":"HONORS THESIS","code":"13124","ctype":"Tut","sec":"C","unit":"4","instructor":"MCCARTHY, J.","weekday":"M","timestr":"6:00-6:50p","stop":time:("18:50:00"),"start":time:("18:00:00"),"place":"TBA","final":"    TBA","max":10,"enr":"0" }
{ "college":"Henry Samueli School of Engineering","dept":"Engineering","course":"HONORS THESIS","code":"13127","ctype":"Tut","sec":"E","unit":"4","instructor":"KHERADVAR, A.","weekday":"M","timestr":"6:00-6:50p","stop":time:("18:50:00"),"start":time:("18:00:00"),"place":"TBA","final":"    TBA","max":10,"enr":"0" }
{ "college":"Henry Samueli School of Engineering","dept":"Engineering","course":"HONORS THESIS","code":"13129","ctype":"Tut","sec":"G","unit":"4","instructor":"WONG, B.","weekday":"M","timestr":"6:00-6:50p","stop":time:("18:50:00"),"start":time:("18:00:00"),"place":"TBA","final":"    TBA","max":10,"enr":"0" }
{ "college":"Henry Samueli School of Engineering","dept":"Engineering","course":"HONORS THESIS","code":"13131","ctype":"Tut","sec":"I","unit":"4","instructor":"VALDEVIT, L.","weekday":"M","timestr":"6:00-6:50p","stop":time:("18:50:00"),"start":time:("18:00:00"),"place":"TBA","final":"    TBA","max":10,"enr":"0" }
{ "college":"Henry Samueli School of Engineering","dept":"Engineering","course":"HONORS THESIS","code":"13133","ctype":"Tut","sec":"K","unit":"4","instructor":"MUKHERJEE, J.","weekday":"M","timestr":"6:00-6:50p","stop":time:("18:50:00"),"start":time:("18:00:00"),"place":"TBA","final":"    TBA","max":10,"enr":"0" }
{ "college":"Henry Samueli School of Engineering","dept":"Engineering","course":"HONORS THESIS","code":"13135","ctype":"Tut","sec":"M","unit":"4","instructor":"CHOI, B.","weekday":"M","timestr":"6:00-6:50p","stop":time:("18:50:00"),"start":time:("18:00:00"),"place":"TBA","final":"    TBA","max":10,"enr":"0" }
{ "college":"Henry Samueli School of Engineering","dept":"Engineering","course":"HONORS THESIS","code":"13137","ctype":"Tut","sec":"O","unit":"4","instructor":"TANG, W.","weekday":"M","timestr":"6:00-6:50p","stop":time:("18:50:00"),"start":time:("18:00:00"),"place":"TBA","final":"    TBA","max":10,"enr":"0" }
{ "college":"Henry Samueli School of Engineering","dept":"Engineering","course":"HONORS THESIS","code":"13139","ctype":"Tut","sec":"Q","unit":"4","instructor":"MOHAMED, F.","weekday":"M","timestr":"6:00-6:50p","stop":time:("18:50:00"),"start":time:("18:00:00"),"place":"TBA","final":"    TBA","max":10,"enr":"1" }
{ "college":"Henry Samueli School of Engineering","dept":"Engineering","course":"HONORS THESIS","code":"13142","ctype":"Tut","sec":"S","unit":"4","instructor":"LARUE, J.","weekday":"M","timestr":"6:00-6:50p","stop":time:("18:50:00"),"start":time:("18:00:00"),"place":"TBA","final":"    TBA","max":10,"enr":"1" }
{ "college":"Henry Samueli School of Engineering","dept":"Engineering","course":"HONORS THESIS","code":"13146","ctype":"Tut","sec":"U","unit":"4","instructor":"SAMUELSEN, S.","weekday":"M","timestr":"6:00-6:50p","stop":time:("18:50:00"),"start":time:("18:00:00"),"place":"TBA","final":"    TBA","max":10,"enr":"1" }
{ "college":"Henry Samueli School of Engineering","dept":"Engineering","course":"INDIVIDUAL STUDY","code":"13200","ctype":"Tut","sec":"A","unit":"1-4","instructor":"LARUE, J.","weekday":" ","timestr":"","place":"TBA","final":"    TBA","max":10,"enr":"0" }
{ "college":"Henry Samueli School of Engineering","dept":"Engineering","course":"INDIV STUDY HONORS","code":"13260","ctype":"Res","sec":"A","unit":"1-5","instructor":"MOHRAZ, A.","weekday":"M","timestr":"7:00-7:50","stop":time:("7:50:00"),"start":time:("7:00:00"),"place":"TBA","final":"    TBA","max":10,"enr":"0" }
{ "college":"Henry Samueli School of Engineering","dept":"Engineering","course":"INDIV STUDY HONORS","code":"13264","ctype":"Res","sec":"C","unit":"1-5","instructor":"RITCHIE, S.","weekday":"M","timestr":"7:00-7:50","stop":time:("7:50:00"),"start":time:("7:00:00"),"place":"TBA","final":"    TBA","max":10,"enr":"0" }
{ "college":"Henry Samueli School of Engineering","dept":"Engineering","course":"INDIV STUDY HONORS","code":"13268","ctype":"Res","sec":"E","unit":"1-5","instructor":"RECKER, W.","weekday":"M","timestr":"7:00-7:50","stop":time:("7:50:00"),"start":time:("7:00:00"),"place":"TBA","final":"    TBA","max":10,"enr":"0" }
{ "college":"Henry Samueli School of Engineering","dept":"Engineering","course":"INDIV STUDY HONORS","code":"13272","ctype":"Res","sec":"G","unit":"1-5","instructor":"ZAREIAN, F.","weekday":"M","timestr":"7:00-7:50","stop":time:("7:50:00"),"start":time:("7:00:00"),"place":"TBA","final":"    TBA","max":10,"enr":"1" }
{ "college":"Henry Samueli School of Engineering","dept":"Engineering","course":"INDIV STUDY HONORS","code":"13275","ctype":"Res","sec":"I","unit":"1-5","instructor":"KHERADVAR, A.","weekday":"M","timestr":"7:00-7:50","stop":time:("7:50:00"),"start":time:("7:00:00"),"place":"TBA","final":"    TBA","max":10,"enr":"0" }
{ "college":"Henry Samueli School of Engineering","dept":"Engineering","course":"INDIV STUDY HONORS","code":"13277","ctype":"Res","sec":"K","unit":"1-5","instructor":"ELTAWIL, A.","weekday":"M","timestr":"7:00-7:50","stop":time:("7:50:00"),"start":time:("7:00:00"),"place":"TBA","final":"    TBA","max":10,"enr":"0" }
{ "college":"Henry Samueli School of Engineering","dept":"Engineering","course":"INDIV STUDY HONORS","code":"13280","ctype":"Res","sec":"M","unit":"1-5","instructor":"HAUN, J.","weekday":"M","timestr":"7:00-7:50","stop":time:("7:50:00"),"start":time:("7:00:00"),"place":"TBA","final":"    TBA","max":10,"enr":"1" }
{ "college":"Henry Samueli School of Engineering","dept":"Engineering","course":"INDIV STUDY HONORS","code":"13284","ctype":"Res","sec":"O","unit":"1-5","instructor":"HUI, E.","weekday":"M","timestr":"7:00-7:50","stop":time:("7:50:00"),"start":time:("7:00:00"),"place":"TBA","final":"    TBA","max":10,"enr":"1" }
{ "college":"Henry Samueli School of Engineering","dept":"Engineering","course":"INDIV STUDY HONORS","code":"13288","ctype":"Res","sec":"Q","unit":"1-5","instructor":"REINKENSMEYER, D.","weekday":" ","timestr":"","place":"TBA","final":"    TBA","max":10,"enr":"1" }
{ "college":"Henry Samueli School of Engineering","dept":"Engineering","course":"INDIV STUDY HONORS","code":"13292","ctype":"Res","sec":"S","unit":"1-5","instructor":"LI, G.","weekday":" ","timestr":"","place":"TBA","final":"    TBA","max":10,"enr":"1" }
{ "college":"Henry Samueli School of Engineering","dept":"Engineering","course":"INDIVIDUAL RESEARCH","code":"13500","ctype":"Res","sec":"A","unit":"1-16","instructor":"LARUE, J.","weekday":" ","timestr":"","place":"TBA","final":"    TBA","max":999,"enr":"0" }
{ "college":"Henry Samueli School of Engineering","dept":"Engineering","course":"UNIVERSITY TEACHING","code":"13600","ctype":"Tut","sec":"A","unit":"4","instructor":"LEE, A.","weekday":"Sa","timestr":"8:00-11:50","stop":time:("11:50:00"),"start":time:("8:00:00"),"place":"NS2 3201","final":"    TBA","max":15,"enr":"4" }
{ "college":"Henry Samueli School of Engineering","dept":"Engineering","course":"UNIVERSITY TEACHING","code":"13620","ctype":"Tut","sec":"C","unit":"4","instructor":"GREEN, M.","weekday":"Sa","timestr":"8:00-11:50","stop":time:("11:50:00"),"start":time:("8:00:00"),"place":"EH 4428","final":"    TBA","max":10,"enr":"0" }
{ "college":"Henry Samueli School of Engineering","dept":"Engineering","course":"UNIVERSITY TEACHING","code":"13640","ctype":"Tut","sec":"E","unit":"4","instructor":"DUNN-RANKIN, D.","weekday":"Sa","timestr":"8:00-11:50","stop":time:("11:50:00"),"start":time:("8:00:00"),"place":"EG S3224","final":"    TBA","max":10,"enr":"0" }
